bm/probability_distributions/__init__.py
bm/probability_distributions/datasets.py
bm/probability_distributions/distribution.py
bm/probability_distributions/py.typed
bm/probability_distributions/distributions/__init__.py
bm/probability_distributions/distributions/binomial.py
bm/probability_distributions/distributions/normal.py
bm/probability_distributions/distributions/py.typed
bm/probability_distributions/distributions/uniform.py
bm_probability_distributions-0.7.1.dist-info/licenses/LICENSE
bm_probability_distributions-0.7.1.dist-info/WHEEL
bm_probability_distributions-0.7.1.dist-info/METADATA
bm_probability_distributions-0.7.1.dist-info/RECORD
