Metadata-Version: 2.4
Name: bm.probability-distributions
Version: 0.7.1
Summary: Visualize probability distributions
Keywords: distribution,probability distributions,sample data
Author-email: "Geoffrey R. Scheller" <geoffrey@scheller.com>
Requires-Python: >=3.12
Classifier: Development Status :: 2 - Pre-Alpha
Classifier: Framework :: Pytest
Classifier: Intended Audience :: Education
Classifier: Intended Audience :: Science/Research
Classifier: License :: OSI Approved :: Apache Software License
Classifier: Operating System :: OS Independent
Classifier: Programming Language :: Python :: 3.13
Classifier: Typing :: Typed
License-File: LICENSE
Requires-Dist: pythonic-fp.fptools >= 3.0.0
Requires-Dist: matplotlib >= 3.10.1
Project-URL: Changelog, https://github.com/grscheller/bm-probability-distributions/blob/main/CHANGELOG.md
Project-URL: Documentation, https://grscheller.github.io/bm-docs/probability-distributions/
Project-URL: Homepage, https://github.com/grscheller/bm-docs/blob/main/README.md
Project-URL: Source, https://github.com/grscheller/bm-probability-distributions
